abatools/__init__.py
abatools/__main__.py
abatools-1.0.0.dist-info/LICENSE
abatools-1.0.0.dist-info/METADATA
abatools-1.0.0.dist-info/NOTICE
abatools-1.0.0.dist-info/WHEEL
abatools-1.0.0.dist-info/entry_points.txt
abatools-1.0.0.dist-info/top_level.txt
abatools-1.0.0.dist-info/RECORD
